{
    "kind": "Template",
    "apiVersion": "v1",
    "metadata": {
        "name": "crunchy-pgbouncer",
        "creationTimestamp": null,
        "annotations": {
            "description": "pgbouncer pod example",
            "iconClass": "icon-database",
            "tags": "database,postgresql,crunchy"
        }
    },
    "parameters": [ {
        "name": "PGBOUNCER_SERVICE_NAME",
        "value": "pgbouncer"
    }, {
        "name": "PVC_ACCESS_MODE",
        "value": "ReadWriteOnce",
        "description": "The accessmode of the pvc"
    }, {
        "name": "CCP_IMAGE_TAG",
        "value": "centos7-10.3-1.8.2",
        "description": "The image tag to pull images with"
    }, {
        "name": "CCP_IMAGE_PREFIX",
        "value": "crunchydata",
        "description": "The image prefix to pull images with"
    } ],
    "objects": [ {
      "kind": "PersistentVolumeClaim",
      "apiVersion": "v1",
      "metadata": {
        "name": "pgbouncer-pvc"
      },
      "spec": {
        "accessModes": [
          "${PVC_ACCESS_MODE}"
        ],
        "resources": {
          "requests": {
            "storage": "10M"
          }
        }
      }
    },
{
        "kind": "Service",
        "apiVersion": "v1",
        "metadata": {
            "name": "${PGBOUNCER_SERVICE_NAME}",
            "labels": {
                "name": "${PGBOUNCER_SERVICE_NAME}"
            }
        },
        "spec": {
            "ports": [{
                "protocol": "TCP",
                "port": 5432,
                "targetPort": 5432,
                "nodePort": 0
            }],
            "selector": {
                "name": "${PGBOUNCER_SERVICE_NAME}"
            }
        },
        "status": {
            "loadBalancer": {}
        }
    }, {
        "kind": "Pod",
        "apiVersion": "v1",
        "metadata": {
            "name": "${PGBOUNCER_SERVICE_NAME}",
            "labels": {
                "name": "${PGBOUNCER_SERVICE_NAME}"
            }
        },
        "spec": {
            "volumes": [{
                "name": "pgconf",
                "persistentVolumeClaim": {
                    "claimName": "pgbouncer-pvc"
                }
            }],
            "containers": [{
                "name": "server",
                "image": "${CCP_IMAGE_PREFIX}/crunchy-pgbouncer:${CCP_IMAGE_TAG}",
                "ports": [{
                    "containerPort": 5432,
                    "protocol": "TCP"
                }],
                "env": [{
                    "name": "PG_DATABASE",
                    "description": "The database name configured in pgbouncer",
                    "value": "postgres"
                }, {
                    "name": "FAILOVER",
                    "description": "failover flag",
                    "value": "yes"
                }, {
                    "name": "OSE_PROJECT",
                    "description": "ose project to login into",
                    "value": "openshift"
                }, {
                    "name": "SLEEP_TIME",
                    "description": "time in secs to sleep between polls",
                    "value": "12"
                }, {
                    "name": "PG_PRIMARY_USER",
                    "description": "The primary user configured in pgbouncer",
                    "value": "primaryuser"
                }, {
                    "name": "PG_PRIMARY_PORT",
                    "description": "The primary port configured in pgbouncer",
                    "value": "5432"
                }, {
                    "name": "PG_PRIMARY_SERVICE",
                    "description": "The primary configured in pgbouncer",
                    "value": "pg-primary-rc-dc"
                }, {
                    "name": "PG_REPLICA_SERVICE",
                    "description": "The replica configured in pgbouncer",
                    "value": "pg-replica-rc-dc"
                }],
                "volumeMounts": [{
                    "mountPath": "/pgconf",
                    "name": "pgconf",
                    "readOnly": true
                }]
            }]
        }
    }]
}
